{
    "description": "path segment",
    "type": "object",
    "properties": {
        "crdtidx": {
            "$ref": "./crdtidx.json"
        },
        "id": {
            "type": "string",
            "minLength": 32,
            "maxLength": 36,
            "default": "$uuid"
        },
        "points": {
            "type": "array",
            "items": {
                "$ref": "./curve-point.json"
            }
        },
        "isClosed": {
            "type": "boolean"
        }
    },
    "required": [
        "crdtidx",
        "id",
        "points",
        "isClosed"
    ],
    "additionalProperties": false
}